{
  "generatedAt": "2026-04-12T05:06:18.527Z",
  "base": {
    "name": "nextclaw",
    "projectRoot": "/home/runner/work/MaxClawLamma/MaxClawLamma",
    "scope": {
      "includeDirs": [
        "apps",
        "packages",
        "workers",
        "bridge",
        "scripts"
      ],
      "includeExtensions": [
        ".ts",
        ".tsx",
        ".js",
        ".jsx",
        ".mjs",
        ".cjs",
        ".sh",
        ".yml",
        ".yaml"
      ],
      "excludeDirs": [
        ".git",
        ".changeset",
        "node_modules",
        "dist",
        "coverage",
        "build",
        "ui-dist",
        ".turbo"
      ]
    },
    "totals": {
      "files": 263,
      "totalLines": 40539,
      "blankLines": 4442,
      "commentLines": 355,
      "codeLines": 35742
    }
  },
  "benchmark": {
    "name": "openclaw",
    "projectRoot": "/home/runner/work/MaxClawLamma/MaxClawLamma/external/openclaw",
    "scope": {
      "includeDirs": [
        "src",
        "extensions",
        "scripts"
      ],
      "includeExtensions": [
        ".ts",
        ".tsx",
        ".js",
        ".jsx",
        ".mjs",
        ".cjs",
        ".sh",
        ".yml",
        ".yaml"
      ],
      "excludeDirs": [
        ".git",
        ".changeset",
        "node_modules",
        "dist",
        "coverage",
        "build",
        "ui-dist",
        ".turbo"
      ]
    },
    "totals": {
      "files": 10660,
      "totalLines": 2061222,
      "blankLines": 178899,
      "commentLines": 33641,
      "codeLines": 1848682
    }
  },
  "comparison": {
    "baseMinusBenchmarkLines": -1812940,
    "basePercentOfBenchmark": 1.93,
    "benchmarkMultipleOfBase": 51.72,
    "baseIsLighterByPercent": 98.07
  }
}
